django_line_notification/__init__.py
django_line_notification/line_notify.py
django_line_notification-1.0.7.dist-info/LICENSE
django_line_notification-1.0.7.dist-info/METADATA
django_line_notification-1.0.7.dist-info/WHEEL
django_line_notification-1.0.7.dist-info/top_level.txt
django_line_notification-1.0.7.dist-info/RECORD
