Metadata-Version: 2.1
Name: django-line-notification
Version: 1.0.7
Summary: UNKNOWN
Home-page: UNKNOWN
Author: Theerapat Singprasert
Author-email: theerapat.pkcn@gmail.com
License: UNKNOWN
Platform: UNKNOWN
License-File: LICENSE
Requires-Dist: requests (>=2.20.0)
